mlservicewrapper/core/__init__.py
mlservicewrapper/core/configuration.py
mlservicewrapper/core/context_sources.py
mlservicewrapper/core/contexts.py
mlservicewrapper/core/errors.py
mlservicewrapper/core/server.py
mlservicewrapper/core/services.py
mlservicewrapper/core/debug/__init__.py
mlservicewrapper/core/debug/__main__.py
mlservicewrapper/core/debug/file_lookups.py
mlservicewrapper/core/debug/local.py
mlservicewrapper/core/debug/profiling.py
mlservicewrapper/core/internal/__init__.py
mlservicewrapper/core/internal/service_loading.py
mlservicewrapper_core-0.7.2.dist-info/LICENSE
mlservicewrapper_core-0.7.2.dist-info/METADATA
mlservicewrapper_core-0.7.2.dist-info/WHEEL
mlservicewrapper_core-0.7.2.dist-info/top_level.txt
mlservicewrapper_core-0.7.2.dist-info/RECORD
