Metadata-Version: 2.1
Name: mlservicewrapper-core
Version: 0.7.2
Summary: Configure a Python service for repeated execution
Home-page: https://github.com/ml-service-wrapper/ml-service-wrapper-core
Author: Matthew Haugen
Author-email: mhaugen@haugenapplications.com
License: UNKNOWN
Platform: UNKNOWN
Requires-Python: >=3.6
Requires-Dist: pandas (~=1.1)
Requires-Dist: mlservicewrapper-config (~=0.3)
